colacloud_mcp/__init__.py
colacloud_mcp/client.py
colacloud_mcp/py.typed
colacloud_mcp/server.py
colacloud_mcp-0.1.0.dist-info/METADATA
colacloud_mcp-0.1.0.dist-info/WHEEL
colacloud_mcp-0.1.0.dist-info/entry_points.txt
colacloud_mcp-0.1.0.dist-info/licenses/LICENSE
colacloud_mcp-0.1.0.dist-info/RECORD
