Metadata-Version: 2.4
Name: colacloud-mcp
Version: 0.1.0
Summary: MCP server for COLA Cloud - access US alcohol label data from AI assistants
Project-URL: Homepage, https://colacloud.us
Project-URL: Documentation, https://app.colacloud.us/docs/api
Project-URL: Repository, https://github.com/cola-cloud-us/colacloud-mcp
Author-email: COLA Cloud <support@colacloud.us>
License-Expression: MIT
License-File: LICENSE
Keywords: ai,alcohol,cola,labels,mcp,ttb
Classifier: Development Status :: 4 - Beta
Classifier: Intended Audience :: Developers
Classifier: License :: OSI Approved :: MIT License
Classifier: Programming Language :: Python :: 3
Classifier: Programming Language :: Python :: 3.10
Classifier: Programming Language :: Python :: 3.11
Classifier: Programming Language :: Python :: 3.12
Requires-Python: >=3.10
Requires-Dist: fastmcp<3,>=2.0.0
Requires-Dist: httpx>=0.27.0
Provides-Extra: dev
Requires-Dist: pytest-asyncio>=0.23.0; extra == 'dev'
Requires-Dist: pytest>=8.0.0; extra == 'dev'
Requires-Dist: respx>=0.21.0; extra == 'dev'
Requires-Dist: ruff>=0.4.0; extra == 'dev'
